asking/VERSION
asking/__init__.py
asking/__main__.py
asking/ask.py
asking/cli.py
asking/exceptions.py
asking/py.typed
asking/state.py
asking/stop_reasons.py
asking/types.py
asking/actions/__init__.py
asking/actions/action.py
asking/actions/ask.py
asking/actions/goto.py
asking/actions/py.typed
asking/actions/responses.py
asking/actions/stop.py
asking/actions/text.py
asking/actions/title.py
asking/loaders/__init__.py
asking/loaders/dict_loader.py
asking/loaders/file_loader.py
asking/loaders/loader.py
asking/loaders/py.typed
asking/loaders/yaml_resource_loader.py
asking/loaders/yaml_string_loader.py
asking/models/__init__.py
asking/models/py.typed
asking/models/script.py
asking/models/stage.py
asking/prompts/__init__.py
asking/prompts/prompt.py
asking/prompts/py.typed
asking/prompts/recall_prompt.py
asking/protocols/__init__.py
asking/protocols/action_protocol.py
asking/protocols/ask_action_protocol.py
asking/protocols/branch_protocol.py
asking/protocols/py.typed
asking/protocols/state_protocol.py
asking/tasks/__init__.py
asking/tasks/perform.py
asking/tasks/py.typed
asking-1.0.3.dist-info/LICENSE
asking-1.0.3.dist-info/METADATA
asking-1.0.3.dist-info/WHEEL
asking-1.0.3.dist-info/entry_points.txt
asking-1.0.3.dist-info/top_level.txt
asking-1.0.3.dist-info/RECORD
