Metadata-Version: 2.1
Name: asking
Version: 1.0.3
Summary: Asking questions and getting answers
Home-page: https://github.com/cariad/asking
Author: Cariad Eccleston
Author-email: cariad@cariad.earth
License: MIT
Classifier: Development Status :: 5 - Production/Stable
Classifier: License :: OSI Approved :: MIT License
Classifier: Natural Language :: English
Classifier: Operating System :: OS Independent
Classifier: Programming Language :: Python :: 3 :: Only
Classifier: Programming Language :: Python :: 3.10
Classifier: Programming Language :: Python :: 3.8
Classifier: Programming Language :: Python :: 3.9
Classifier: Typing :: Typed
Requires-Python: >=3.8
License-File: LICENSE
Requires-Dist: ansiscape (~=1.1.2)
Requires-Dist: ansiwrap (~=0.8)
Requires-Dist: cline (~=1.1)
Requires-Dist: pyyaml (~=6.0)
